calculator_ab/__init__.py
calculator_ab-0.5.0.dist-info/WHEEL
calculator_ab-0.5.0.dist-info/METADATA
calculator_ab-0.5.0.dist-info/RECORD
