Metadata-Version: 2.1
Name: calculator_ab
Version: 0.5.0
Summary: A calculator.
Author-email: Andrius_B <andrius@b.org>
